{
  "collapse-filter": true,
  "search": "",
  "showTags": false,
  "showAttachments": false,
  "hideUnresolved": false,
  "showOrphans": true,
  "collapse-color-groups": true,
  "colorGroups": [
    {
      "query": "IP Connectivity",
      "color": {
        "a": 1,
        "rgb": 37375
      }
    },
    {
      "query": "IP Security",
      "color": {
        "a": 1,
        "rgb": 15609730
      }
    },
    {
      "query": "IP Services",
      "color": {
        "a": 1,
        "rgb": 11657298
      }
    },
    {
      "query": "Network Access",
      "color": {
        "a": 1,
        "rgb": 16514826
      }
    },
    {
      "query": "Network Fundamentals",
      "color": {
        "a": 1,
        "rgb": 1376177
      }
    }
  ],
  "collapse-display": false,
  "showArrow": false,
  "textFadeMultiplier": 0,
  "nodeSizeMultiplier": 1,
  "lineSizeMultiplier": 1,
  "collapse-forces": true,
  "centerStrength": 0.518713248970312,
  "repelStrength": 10,
  "linkStrength": 1,
  "linkDistance": 250,
  "scale": 0.36288736930121435,
  "close": false
}